{
  "ingredientes": {
    "paes": [
      {
        "id": 1,
        "tipo": "Italiano Branco"
      },
      {
        "id": 2,
        "tipo": "3 Queijos"
      },
      {
        "id": 3,
        "tipo": "Parmesão e Orégano"
      },
      {
        "id": 4,
        "tipo": "Integral"
      }
    ],
    "carnes": [
      {
        "id": 1,
        "tipo": "Maminha"
      },
      {
        "id": 2,
        "tipo": "Alcatra"
      },
      {
        "id": 3,
        "tipo": "Picanha"
      },
      {
        "id": 4,
        "tipo": "Veggie burger"
      }
    ],
    "opcionais": [
      {
        "id": 1,
        "tipo": "Bacon"
      },
      {
        "id": 2,
        "tipo": "Cheddar"
      },
      {
        "id": 3,
        "tipo": "Salame"
      },
      {
        "id": 4,
        "tipo": "Tomate"
      },
      {
        "id": 4,
        "tipo": "Cebola roxa"
      },
      {
        "id": 4,
        "tipo": "Pepino"
      }
    ]
  },
  "status": [
    {
      "id": 1,
      "tipo": "Solicitado"
    },
    {
      "id": 2,
      "tipo": "Em produção"
    },
    {
      "id": 3,
      "tipo": "Finalizado"
    }
  ],
  "burgers": [
    {
      "nome": "Vitor",
      "carne": "Maminha",
      "pao": "Italiano Branco",
      "opcionais": [],
      "status": "Solicitado",
      "id": 1
    },
    {
      "nome": "ddd",
      "carne": "Maminha",
      "pao": "Italiano Branco",
      "opcionais": [],
      "status": "Solicitado",
      "id": 2
    },
    {
      "nome": "adasda",
      "carne": "Alcatra",
      "pao": "Italiano Branco",
      "opcionais": [],
      "status": "Solicitado",
      "id": 3
    },
    {
      "nome": "heehhe",
      "carne": "Picanha",
      "pao": "3 Queijos",
      "opcionais": [
        "Bacon",
        "Tomate"
      ],
      "status": "Solicitado",
      "id": 4
    },
    {
      "nome": "adsda",
      "carne": "Alcatra",
      "pao": "3 Queijos",
      "opcionais": [
        "Salame"
      ],
      "status": "Solicitado",
      "id": 5
    },
    {
      "nome": "sadad",
      "carne": "Picanha",
      "pao": "Parmesão e Orégano",
      "opcionais": [
        "Bacon"
      ],
      "status": "Solicitado",
      "id": 6
    },
    {
      "nome": "Guastavo",
      "carne": "Picanha",
      "pao": "3 Queijos",
      "opcionais": [
        "Bacon",
        "Cebola roxa",
        "Cheddar",
        "Pepino"
      ],
      "status": "Solicitado",
      "id": 7
    },
    {
      "nome": "Vitor",
      "carne": "Maminha",
      "pao": null,
      "opcionais": [
        "Bacon"
      ],
      "status": "Solicitado",
      "id": 8
    },
    {
      "nome": null,
      "carne": "Alcatra",
      "pao": "3 Queijos",
      "opcionais": [
        "Bacon"
      ],
      "status": "Solicitado",
      "id": 9
    },
    {
      "nome": "Vitor",
      "carne": "Alcatra",
      "pao": "Italiano Branco",
      "opcionais": [
        "Cheddar",
        "Cebola roxa"
      ],
      "status": "Solicitado",
      "id": 10
    },
    {
      "nome": "Maria Luiza ",
      "carne": "Picanha",
      "pao": "3 Queijos",
      "opcionais": [
        "Bacon",
        "Cheddar"
      ],
      "status": "Solicitado",
      "id": 11
    }
  ]
}